LICENSE
MANIFEST.in
README.rst
setup.py
assume/__init__.py
assume/__init__.pyc
assume/admin_urls.py
assume/admin_urls.pyc
assume/backends.py
assume/backends.pyc
assume/views.py
assume/views.pyc
assume/templates/admin/auth/user/change_form.html
django_assume.egg-info/PKG-INFO
django_assume.egg-info/SOURCES.txt
django_assume.egg-info/dependency_links.txt
django_assume.egg-info/not-zip-safe
django_assume.egg-info/requires.txt
django_assume.egg-info/top_level.txt