Metadata-Version: 1.1
Name: django-assume
Version: 0.2.1
Summary: Django app that allows administrators to log in to user accounts without having to provide a password
Home-page: https://github.com/bryanchow/django-assume
Author: Bryan Chow
Author-email: UNKNOWN
License: WTFPL
Download-URL: https://github.com/bryanchow/django-assume/tarball/master
Platform: UNKNOWN
